setup.py
crawling/__init__.py
crawling/cli.py
crawling/crawling.py
crawling.egg-info/PKG-INFO
crawling.egg-info/SOURCES.txt
crawling.egg-info/dependency_links.txt
crawling.egg-info/entry_points.txt
crawling.egg-info/requires.txt
crawling.egg-info/top_level.txt