Metadata-Version: 1.0
Name: crawling
Version: 0.1
Summary: A tiny spider suite
Home-page: https://github.com/pandada8/crawling
Author: pandada8
Author-email: pandada8@gmail.com
License: MIT
Platform: UNKNOWN
